mtcnn_tflite/MTCNN.py
mtcnn_tflite/ModelBuilder.py
mtcnn_tflite/__init__.py
mtcnn_tflite/data/mtcnn_weights.npy
mtcnn_tflite/exceptions/__init__.py
mtcnn_tflite/exceptions/invalid_image.py
mtcnn_tflite-0.0.4.dist-info/LICENSE
mtcnn_tflite-0.0.4.dist-info/METADATA
mtcnn_tflite-0.0.4.dist-info/WHEEL
mtcnn_tflite-0.0.4.dist-info/top_level.txt
mtcnn_tflite-0.0.4.dist-info/RECORD
