Metadata-Version: 2.1
Name: mtcnn-tflite
Version: 0.0.4
Summary: MTCNN face detection implementation in Tensorflow Lite.
Home-page: https://github.com/mobilesec/mtcnn-tflite
Author: Philipp Hofer
Author-email: philipp.hofer@ins.jku.at
License: MIT License
Platform: UNKNOWN
Classifier: License :: OSI Approved :: MIT License
Classifier: Programming Language :: Python :: 3
Classifier: Operating System :: OS Independent
Requires-Dist: tensorflow (>=2.0.0)
Requires-Dist: numpy
Requires-Dist: opencv-python (>=4.4)
Requires-Dist: fcache (>=0.4.0)
